fancy/config/__init__.py
fancy/config/__init__.pyi
fancy/config/attribute_setters.py
fancy/config/base_config.py
fancy/config/config_context.py
fancy/config/config_factory.py
fancy/config/config_list_struct.py
fancy/config/config_loader_factory.py
fancy/config/config_loaders.py
fancy/config/config_structure.py
fancy/config/config_structure_visitor.py
fancy/config/consts.py
fancy/config/exc.py
fancy/config/lazy.py
fancy/config/option.py
fancy/config/placeholder.py
fancy/config/typing.py
fancy/config/converter/__init__.py
fancy/config/converter/base_option_converter.py
fancy/config/process/__init__.py
fancy/config/process/auto_process_typ.py
fancy/config/process/auto_process_value.py
fancy/config/process/boolean.py
fancy/config/process/config.py
fancy/config/process/config_list.py
fancy/config/process/flag_container.py
fancy/config/process/flag_string.py
fancy/config/process/identical.py
fancy/config/utils/__init__.py
fancy/config/utils/dispatch.py
fancy/config/utils/inspect.py
fancy/config/utils/reflections.py
fancy/config/visitors/__init__.py
fancy/config/visitors/to_collection_visitor.py
fancy_config-0.13.4.dist-info/LICENSE.txt
fancy_config-0.13.4.dist-info/METADATA
fancy_config-0.13.4.dist-info/WHEEL
fancy_config-0.13.4.dist-info/top_level.txt
fancy_config-0.13.4.dist-info/RECORD
