Metadata-Version: 2.1
Name: fancy-config
Version: 0.13.4
Summary: config
Home-page: UNKNOWN
Author: su-rin
Author-email: susautw@gmail.com
License: MIT
Project-URL: Source Code, https://github.com/susautw/fancy-config
Keywords: config
Platform: UNKNOWN
Classifier: Programming Language :: Python :: 3
Classifier: License :: OSI Approved :: MIT License
Classifier: Operating System :: OS Independent
Requires-Python: >=3.6
License-File: LICENSE.txt
Requires-Dist: PyYAML (~=6.0)
